{"cameraMode":{"drawMode":0,"name":"Shaded","section":"Shading Mode"},"sceneLighting":false,"audioPlay":false,"sceneViewState":{"m_AlwaysRefresh":false,"showFog":true,"showSkybox":false,"showFlares":true,"showImageEffects":true,"showParticleSystems":true,"showVisualEffectGraphs":true,"m_FxEnabled":true},"in2DMode":false,"pivot":{"x":8.038740158081055,"y":0.3001645803451538,"z":-13.670000076293946},"rotation":{"x":-0.36656653881073,"y":0.0022530921269208194,"z":-0.0008599342545494437,"w":-0.9304090738296509},"size":0.7948678135871887,"orthographic":false}